track_linearization/__init__.py
track_linearization/_version.py
track_linearization/core.py
track_linearization/track_builders.py
track_linearization/utils.py
track_linearization/validation.py
track_linearization/tests/test_core.py
track_linearization/tests/test_import.py
track_linearization/tests/test_track_builders.py
track_linearization/tests/test_utils.py
track_linearization/tests/test_validation.py
track_linearization-2.4.0.dist-info/METADATA
track_linearization-2.4.0.dist-info/WHEEL
track_linearization-2.4.0.dist-info/licenses/LICENSE
track_linearization-2.4.0.dist-info/RECORD
