Metadata-Version: 2.4
Name: track_linearization
Version: 2.4.0
Summary: A python package to map 2D trajectories to 1D.
Project-URL: Homepage, https://github.com/LorenFrankLab/track_linearization
Project-URL: Bug Tracker, https://github.com/LorenFrankLab/track_linearization/issues
Author-email: Eric Denovellis <eric.denovellis@ucsf.edu>
License: MIT License
License-File: LICENSE
Classifier: Development Status :: 4 - Beta
Classifier: Intended Audience :: Science/Research
Classifier: License :: OSI Approved :: MIT License
Classifier: Operating System :: OS Independent
Classifier: Programming Language :: Python :: 3
Classifier: Programming Language :: Python :: 3.10
Classifier: Programming Language :: Python :: 3.11
Classifier: Programming Language :: Python :: 3.12
Classifier: Programming Language :: Python :: 3.13
Classifier: Topic :: Scientific/Engineering
Requires-Python: >=3.10
Requires-Dist: dask[array]>=2023.5.0
Requires-Dist: matplotlib>=3.7
Requires-Dist: networkx>=3.2.1
Requires-Dist: numpy>=1.24
Requires-Dist: pandas>=2.0
Requires-Dist: scipy>=1.10
Provides-Extra: dev
Requires-Dist: black; extra == 'dev'
Requires-Dist: jupyter; extra == 'dev'
Requires-Dist: mypy; extra == 'dev'
Requires-Dist: nbconvert; extra == 'dev'
Requires-Dist: pandas-stubs; extra == 'dev'
Requires-Dist: pre-commit; extra == 'dev'
Requires-Dist: pytest; extra == 'dev'
Requires-Dist: pytest-cov; extra == 'dev'
Requires-Dist: ruff; extra == 'dev'
Provides-Extra: opt
Requires-Dist: ipympl; extra == 'opt'
Requires-Dist: numba; extra == 'opt'
Provides-Extra: test
Requires-Dist: black; extra == 'test'
Requires-Dist: jupyter; extra == 'test'
Requires-Dist: mypy; extra == 'test'
Requires-Dist: nbconvert; extra == 'test'
Requires-Dist: pandas-stubs; extra == 'test'
Requires-Dist: pytest; extra == 'test'
Requires-Dist: pytest-cov; extra == 'test'
Requires-Dist: ruff; extra == 'test'
